README.md
setup.py
newpkg/__init__.py
newpkg/__main__.py
newpkg.egg-info/PKG-INFO
newpkg.egg-info/SOURCES.txt
newpkg.egg-info/dependency_links.txt
newpkg.egg-info/entry_points.txt
newpkg.egg-info/requires.txt
newpkg.egg-info/top_level.txt